RedditAdsWindsorApi/__init__.py
RedditAdsWindsorApi/client.py
RedditAdsWindsorApi/enums.py
test/__init__.py
test/tests.py
RedditAdsWindsorApi-1.0.6.dist-info/METADATA
RedditAdsWindsorApi-1.0.6.dist-info/WHEEL
RedditAdsWindsorApi-1.0.6.dist-info/top_level.txt
RedditAdsWindsorApi-1.0.6.dist-info/RECORD
