Metadata-Version: 2.1
Name: RedditAdsWindsorApi
Version: 1.0.6
Summary: Easy access to windsor.ai Reddit APIs
Home-page: https://github.com/windsor-ai/RedditAdsWindsorApi
Author: Windsor AI
Author-email: dev@windsor.ai
Requires-Dist: requests (~=2.25.1)
